Workbook

Sheet 00_Instrucciones
B2: Protocolo de validacion de LucIA — banco de 50 preguntas
B3: Ejecuta las reglas VAL-001, VAL-002 y VAL-003 del checklist, que quedaron FUERA_DE_ALCANCE en la auditoria auditoria_20260815_135308.xlsx (15 documentos, 34 reglas).
B5: Para que sirve
B6: El problema | C6: La auditoria mide la calidad de los PDFs, no las respuestas de LucIA. Sin una medicion de partida no se puede demostrar que los documentos corregidos mejoren nada.
B7: La solucion | C7: Se lanzan las mismas 50 preguntas dos veces: V0 con el corpus actual (ANTES de subir nada) y V1 con el corpus corregido. La hoja 04 compara pregunta a pregunta.
B8: Regla de oro | C8: V0 debe ejecutarse ANTES de subir ningun documento nuevo. Si se sube algo primero, la linea base se pierde y el retesting deja de ser comparable.
B10: Como se usa
B11: 1. Congelar | C11: No tocar el corpus. Anotar en la celda C40 la fecha de ejecucion de V0.
B12: 2. Lanzar V0 | C12: Copiar cada pregunta de la hoja 02 en LucIA, tal cual, en sesiones independientes (sin historial previo, para que una respuesta no contamine la siguiente).
B13: 3. Puntuar | C13: Rellenar SOLO las celdas amarillas de la hoja 02. El veredicto y los puntos se calculan solos.
B14: 4. Corregir | C14: Subir los documentos corregidos al corpus de LucIA.
B15: 5. Lanzar V1 | C15: Repetir el proceso en la hoja 03, con las mismas 50 preguntas.
B16: 6. Comparar | C16: Las hojas 04 y 05 muestran la evolucion por pregunta, por categoria y por documento.
B18: Que se puntua en cada pregunta
B19: cita_ok (VAL-002) | C19: SI = cita el documento esperado. PARCIAL = lo cita junto a otros no pertinentes. NO = cita un documento equivocado. NO_CITA = responde sin citar fuente.
B20: exactitud (VAL-003) | C20: LITERAL = coincide con el contenido del documento. PARCIAL = incompleta pero sin errores. INVENTADA = afirma datos que no estan en la documentacion. NO_RESPONDE = no contesta.
B21: veredicto | C21: Se calcula: ACIERTO (1 pto) · PARCIAL (0,5) · FALLO (0) · SIN_RESPUESTA (0) · ALUCINACION (-1).
B22: Por que -1 | C22: Una alucinacion es peor que un silencio: el agente la traslada al cliente como si fuera cierta.
B24: Las seis categorias del banco
B25: A_DESAMBIGUACION (14) | C25: Productos vecinos que comparten vocabulario. Mide TAX-007/TAX-008/META-006, que fallan en los 15 documentos: ninguno tiene bloque "No confundir con".
B26: B_SINONIMOS (12) | C26: Lenguaje coloquial real de los agentes. Mide TAX-010/META-007, que fallan en los 15.
B27: C_TABLAS_PERDIDAS (8) | C27: Datos que viven en tablas y capturas que la extraccion de texto perdio. Aqui la respuesta correcta suele ser "no dispongo del dato": cualquier cifra concreta es alucinacion.
B28: D_TRAMPA (6) | C28: Preguntas cuya respuesta correcta es una negativa o un "no consta". Detectan invencion.
B29: E_LITERAL (8) | C29: Control positivo: datos que si constan literalmente. Un fallo aqui apunta a la recuperacion, no a la taxonomia.
B30: F_TRAZABILIDAD (2) | C30: Normativa de origen. Mide META-009, que solo cumplen 2 de los 15 documentos.
B32: Ejemplo de fila ya cumplimentada (hoja 02 o 03)
B33: id | C33: D01
B34: respuesta_de_lucia (E) | C34: Si, se tramita desde la Oficina del Instalador aportando el certificado de vulnerabilidad.
B35: doc_citado (F) | C35: 000001052 Bono Social
B36: cita_ok (G) | C36: SI
B37: exactitud (H) | C37: INVENTADA
B38: -> veredicto | C38: ALUCINACION
B39: Fecha de ejecucion V0 | C39: -1
B40: Fecha de ejecucion V1 | C40: Lectura: LucIA cita el documento correcto pero afirma que Fenie Energia puede tramitar el Bono Social. Cita bien y responde mal — el caso mas peligroso, y el que la auditoria documental no detecta.
B41: Responsable
B42: Leyenda de formato
B43: Origen de los datos | C43: Unicas celdas que debes rellenar a mano.
B44: Fondo gris | C44: Las 50 preguntas se derivan de la evidencia textual citada en auditoria_20260815_135308.xlsx (hoja Reglas, columna evidencia) y de los metadatos RAG extraidos por documento. No hay preguntas inventadas al margen del corpus.
B45: Sin fondo | C45: Datos de referencia del banco de preguntas.

Sheet 01_Banco_preguntas
A1: id | B1: categoria | C1: pregunta | D1: doc_esperado_id | E1: doc_esperado_nombre | F1: docs_implicados | G1: respuesta_correcta_esperada | H1: reglas_auditoria | I1: fallo_previsto | J1: clave_doc
A2: A01 | B2: A_DESAMBIGUACION | C2: Quiero cambiar solo la potencia contratada de un suministro, sin tocar la tarifa. Que procedimiento aplico? | D2: 000001630 | E2: Modificacion de potencias en electricidad | F2: 000001630 / 000001631 | G2: Debe citar el procedimiento de Modificacion de potencias (000001630), NO el de Modificacion de tarifa y potencias (000001631). | H2: TAX-007, TAX-008, META-006 | I2: Cita 000001631 o mezcla ambos: ningun documento tiene bloque 'No confundir con'. | J2: D000001630
A3: A02 | B3: A_DESAMBIGUACION | C3: Necesito cambiar la tarifa y la potencia a la vez. Es el mismo tramite que cambiar solo la potencia? | D3: 000001631 | E3: Modificacion de tarifa y potencias en electricidad | F3: 000001630 / 000001631 | G3: NO. Existe un procedimiento propio 'Modificacion de tarifa y potencias' (000001631), distinto del de solo potencias (000001630). | H3: TAX-007, TAX-008 | I3: Responde que si, o cita un unico documento sin advertir que son tramites distintos. | J3: D000001631
A4: A03 | B4: A_DESAMBIGUACION | C4: Que diferencia hay entre una modificacion de producto y una modificacion de tarifa? | D4: 000001634 | E4: Modificacion de producto | F4: 000001634 / 000001631 | G4: Producto = cambiar el producto contratado, via Modificaciones Administrativas (000001634). Tarifa y potencias = modificacion tecnica (000001631). | H4: TAX-007, TAX-008, META-006 | I4: Mezcla ambos conceptos o inventa la diferencia. | J4: D000001634
A5: A04 | B5: A_DESAMBIGUACION | C5: Quiero cambiar la cuenta bancaria del cliente. Que modificacion uso? | D5: 000008614 | E5: Modificacion de los Datos de Facturacion | F5: 000008614 / 000008619 | G5: Datos de Facturacion (000008614): sirve para correo de facturacion, direccion postal, cuenta bancaria y metodo de pago. | H5: TAX-007, TAX-008 | I5: Cita 000008619 'Datos de Contrato' por solapamiento de vocabulario. | J5: D000008614
A6: A05 | B6: A_DESAMBIGUACION | C6: Cambiar el telefono de contacto del punto de suministro es lo mismo que cambiar el telefono de contratacion? | D6: 000008617 | E6: Modificacion de Datos de Contacto del Punto de Suministro | F6: 000008617 / 000008619 | G6: NO. Punto de suministro = 000008617. Telefono de contratacion = Datos de Contrato (000008619). | H6: TAX-007, TAX-008 | I6: Confunde los dos documentos: ambos hablan de 'telefono' sin desambiguar. | J6: D000008617
A7: A06 | B7: A_DESAMBIGUACION | C7: Donde cambio el correo al que se le envia la factura al cliente? | D7: 000008614 | E7: Modificacion de los Datos de Facturacion | F7: 000008614 / 000008619 | G7: Datos de Facturacion (000008614): 'cambiar el correo de facturacion, o anadir un segundo correo'. NO es el correo de contratacion (000008619). | H7: TAX-007, TAX-008 | I7: Cita 000008619, que tambien gestiona un correo (el de contratacion). | J7: D000008614
A8: A07 | B8: A_DESAMBIGUACION | C8: El cliente es una comunidad de propietarios y ha cambiado el presidente. Hago un cambio de titular o una modificacion de representante? | D8: 000008616 | E8: Modificacion de datos del representante | F8: 000008616 / 000001633 | G8: Modificacion de datos del representante (000008616), que aplica expresamente a empresas y comunidades de propietarios. NO cambio de titular. | H8: TAX-007, TAX-008, META-006 | I8: Cita 000001633 (cambio de titular) por la palabra clave compartida 'titular'. | J8: D000008616
A9: A08 | B9: A_DESAMBIGUACION | C9: Que diferencia hay entre cambiar el titular de un contrato y cambiar el representante? | D9: 000001633 | E9: Cambio de titular en electricidad y gas | F9: 000001633 / 000008616 | G9: Titular = la persona/empresa que contrata (000001633). Representante = quien firma en su nombre (000008616), requiere DNI/NIE del nuevo representante. | H9: TAX-007, TAX-008 | I9: No sabe distinguirlos: ninguno de los dos PDFs explica la diferencia. | J9: D000001633
A10: A09 | B10: A_DESAMBIGUACION | C10: Monedero Solar y autoconsumo son lo mismo? | D10: 000008620 | E10: Monedero Solar | F10: 000008620 / 000008621 | G10: NO. Autoconsumo (000008621) = activar la modalidad de autoconsumo en el contrato. Monedero Solar (000008620) = servicio que acumula en euros el saldo de excedentes NO compensados. | H10: TAX-007, TAX-008, META-006 | I10: Los trata como sinonimos. El propio informe marca Monedero Solar como 'producto vecino' de autoconsumo. | J10: D000008620
A11: A10 | B11: A_DESAMBIGUACION | C11: El cliente tiene placas y le sobra energia que no se le compensa en la factura. Que le activo? | D11: 000008620 | E11: Monedero Solar | F11: 000008620 / 000008621 | G11: Monedero Solar (000008620): acumula el saldo sobrante de los excedentes no compensados en euros y se aplica despues de impuestos al resto de conceptos de la factura. | H11: TAX-007, TAX-008 | I11: Cita autoconsumo (000008621) en lugar de Monedero Solar. | J11: D000008620
A12: A11 | B12: A_DESAMBIGUACION | C12: Modificar el maximetro es lo mismo que modificar la potencia contratada? | D12: 000008622 | E12: Modificacion de Maximetro | F12: 000008622 / 000001630 | G12: NO. Son dos modificaciones tecnicas distintas: Maximetro (000008622) y Modificacion de potencias (000001630). Ambas de ATR. | H12: TAX-007, TAX-008 | I12: Los funde: ambos son 'modificaciones tecnicas' del departamento ATR. | J12: D000008622
... A51: F02 | B51: F_TRAZABILIDAD | C51: Que norma regula los plazos del autoconsumo? | D51: 000008621 | E51: Modificacion de autoconsumo | F51: 000008621 | G51: Orden TED/1247/2021, de 15 de noviembre. | H51: META-009 | I51: La norma se cita de pasada, sin seccion de fuentes. Puede no recuperarla. | J51: D000008621

Sheet 02_Ejecucion_V0
A1: id | B1: categoria | C1: pregunta | D1: doc_esperado | E1: respuesta_de_lucia | F1: doc_citado_por_lucia | G1: cita_ok | H1: exactitud | I1: veredicto | J1: puntos | K1: observaciones
A2: ='01_Banco_preguntas'!A2 | B2: ='01_Banco_preguntas'!B2 | C2: ='01_Banco_preguntas'!C2 | D2: ='01_Banco_preguntas'!D2&" "&'01_Banco_preguntas'!E2 | I2: =IF(OR($G2="",$H2=""),"",IF($H2="INVENTADA","ALUCINACION",IF($H2="NO_RESPONDE","SIN_RESPUESTA",IF(AND($G2="SI",$H2="LITERAL"),"ACIERTO",IF(OR($G2="NO",$G2="NO_CITA"),"FALLO","PARCIAL"))))) | J2: =IF($I2="","",IF($I2="ACIERTO",1,IF($I2="PARCIAL",0.5,IF($I2="ALUCINACION",-1,0))))
A3: ='01_Banco_preguntas'!A3 | B3: ='01_Banco_preguntas'!B3 | C3: ='01_Banco_preguntas'!C3 | D3: ='01_Banco_preguntas'!D3&" "&'01_Banco_preguntas'!E3 | I3: =IF(OR($G3="",$H3=""),"",IF($H3="INVENTADA","ALUCINACION",IF($H3="NO_RESPONDE","SIN_RESPUESTA",IF(AND($G3="SI",$H3="LITERAL"),"ACIERTO",IF(OR($G3="NO",$G3="NO_CITA"),"FALLO","PARCIAL"))))) | J3: =IF($I3="","",IF($I3="ACIERTO",1,IF($I3="PARCIAL",0.5,IF($I3="ALUCINACION",-1,0))))
A4: ='01_Banco_preguntas'!A4 | B4: ='01_Banco_preguntas'!B4 | C4: ='01_Banco_preguntas'!C4 | D4: ='01_Banco_preguntas'!D4&" "&'01_Banco_preguntas'!E4 | I4: =IF(OR($G4="",$H4=""),"",IF($H4="INVENTADA","ALUCINACION",IF($H4="NO_RESPONDE","SIN_RESPUESTA",IF(AND($G4="SI",$H4="LITERAL"),"ACIERTO",IF(OR($G4="NO",$G4="NO_CITA"),"FALLO","PARCIAL"))))) | J4: =IF($I4="","",IF($I4="ACIERTO",1,IF($I4="PARCIAL",0.5,IF($I4="ALUCINACION",-1,0))))
A5: ='01_Banco_preguntas'!A5 | B5: ='01_Banco_preguntas'!B5 | C5: ='01_Banco_preguntas'!C5 | D5: ='01_Banco_preguntas'!D5&" "&'01_Banco_preguntas'!E5 | I5: =IF(OR($G5="",$H5=""),"",IF($H5="INVENTADA","ALUCINACION",IF($H5="NO_RESPONDE","SIN_RESPUESTA",IF(AND($G5="SI",$H5="LITERAL"),"ACIERTO",IF(OR($G5="NO",$G5="NO_CITA"),"FALLO","PARCIAL"))))) | J5: =IF($I5="","",IF($I5="ACIERTO",1,IF($I5="PARCIAL",0.5,IF($I5="ALUCINACION",-1,0))))
A6: ='01_Banco_preguntas'!A6 | B6: ='01_Banco_preguntas'!B6 | C6: ='01_Banco_preguntas'!C6 | D6: ='01_Banco_preguntas'!D6&" "&'01_Banco_preguntas'!E6 | I6: =IF(OR($G6="",$H6=""),"",IF($H6="INVENTADA","ALUCINACION",IF($H6="NO_RESPONDE","SIN_RESPUESTA",IF(AND($G6="SI",$H6="LITERAL"),"ACIERTO",IF(OR($G6="NO",$G6="NO_CITA"),"FALLO","PARCIAL"))))) | J6: =IF($I6="","",IF($I6="ACIERTO",1,IF($I6="PARCIAL",0.5,IF($I6="ALUCINACION",-1,0))))
A7: ='01_Banco_preguntas'!A7 | B7: ='01_Banco_preguntas'!B7 | C7: ='01_Banco_preguntas'!C7 | D7: ='01_Banco_preguntas'!D7&" "&'01_Banco_preguntas'!E7 | I7: =IF(OR($G7="",$H7=""),"",IF($H7="INVENTADA","ALUCINACION",IF($H7="NO_RESPONDE","SIN_RESPUESTA",IF(AND($G7="SI",$H7="LITERAL"),"ACIERTO",IF(OR($G7="NO",$G7="NO_CITA"),"FALLO","PARCIAL"))))) | J7: =IF($I7="","",IF($I7="ACIERTO",1,IF($I7="PARCIAL",0.5,IF($I7="ALUCINACION",-1,0))))
A8: ='01_Banco_preguntas'!A8 | B8: ='01_Banco_preguntas'!B8 | C8: ='01_Banco_preguntas'!C8 | D8: ='01_Banco_preguntas'!D8&" "&'01_Banco_preguntas'!E8 | I8: =IF(OR($G8="",$H8=""),"",IF($H8="INVENTADA","ALUCINACION",IF($H8="NO_RESPONDE","SIN_RESPUESTA",IF(AND($G8="SI",$H8="LITERAL"),"ACIERTO",IF(OR($G8="NO",$G8="NO_CITA"),"FALLO","PARCIAL"))))) | J8: =IF($I8="","",IF($I8="ACIERTO",1,IF($I8="PARCIAL",0.5,IF($I8="ALUCINACION",-1,0))))
A9: ='01_Banco_preguntas'!A9 | B9: ='01_Banco_preguntas'!B9 | C9: ='01_Banco_preguntas'!C9 | D9: ='01_Banco_preguntas'!D9&" "&'01_Banco_preguntas'!E9 | I9: =IF(OR($G9="",$H9=""),"",IF($H9="INVENTADA","ALUCINACION",IF($H9="NO_RESPONDE","SIN_RESPUESTA",IF(AND($G9="SI",$H9="LITERAL"),"ACIERTO",IF(OR($G9="NO",$G9="NO_CITA"),"FALLO","PARCIAL"))))) | J9: =IF($I9="","",IF($I9="ACIERTO",1,IF($I9="PARCIAL",0.5,IF($I9="ALUCINACION",-1,0))))
A10: ='01_Banco_preguntas'!A10 | B10: ='01_Banco_preguntas'!B10 | C10: ='01_Banco_preguntas'!C10 | D10: ='01_Banco_preguntas'!D10&" "&'01_Banco_preguntas'!E10 | I10: =IF(OR($G10="",$H10=""),"",IF($H10="INVENTADA","ALUCINACION",IF($H10="NO_RESPONDE","SIN_RESPUESTA",IF(AND($G10="SI",$H10="LITERAL"),"ACIERTO",IF(OR($G10="NO",$G10="NO_CITA"),"FALLO","PARCIAL"))))) | J10: =IF($I10="","",IF($I10="ACIERTO",1,IF($I10="PARCIAL",0.5,IF($I10="ALUCINACION",-1,0))))
A11: ='01_Banco_preguntas'!A11 | B11: ='01_Banco_preguntas'!B11 | C11: ='01_Banco_preguntas'!C11 | D11: ='01_Banco_preguntas'!D11&" "&'01_Banco_preguntas'!E11 | I11: =IF(OR($G11="",$H11=""),"",IF($H11="INVENTADA","ALUCINACION",IF($H11="NO_RESPONDE","SIN_RESPUESTA",IF(AND($G11="SI",$H11="LITERAL"),"ACIERTO",IF(OR($G11="NO",$G11="NO_CITA"),"FALLO","PARCIAL"))))) | J11: =IF($I11="","",IF($I11="ACIERTO",1,IF($I11="PARCIAL",0.5,IF($I11="ALUCINACION",-1,0))))
A12: ='01_Banco_preguntas'!A12 | B12: ='01_Banco_preguntas'!B12 | C12: ='01_Banco_preguntas'!C12 | D12: ='01_Banco_preguntas'!D12&" "&'01_Banco_preguntas'!E12 | I12: =IF(OR($G12="",$H12=""),"",IF($H12="INVENTADA","ALUCINACION",IF($H12="NO_RESPONDE","SIN_RESPUESTA",IF(AND($G12="SI",$H12="LITERAL"),"ACIERTO",IF(OR($G12="NO",$G12="NO_CITA"),"FALLO","PARCIAL"))))) | J12: =IF($I12="","",IF($I12="ACIERTO",1,IF($I12="PARCIAL",0.5,IF($I12="ALUCINACION",-1,0))))
A13: ='01_Banco_preguntas'!A13 | B13: ='01_Banco_preguntas'!B13 | C13: ='01_Banco_preguntas'!C13 | D13: ='01_Banco_preguntas'!D13&" "&'01_Banco_preguntas'!E13 | I13: =IF(OR($G13="",$H13=""),"",IF($H13="INVENTADA","ALUCINACION",IF($H13="NO_RESPONDE","SIN_RESPUESTA",IF(AND($G13="SI",$H13="LITERAL"),"ACIERTO",IF(OR($G13="NO",$G13="NO_CITA"),"FALLO","PARCIAL"))))) | J13: =IF($I13="","",IF($I13="ACIERTO",1,IF($I13="PARCIAL",0.5,IF($I13="ALUCINACION",-1,0))))
... A51: ='01_Banco_preguntas'!A51 | B51: ='01_Banco_preguntas'!B51 | C51: ='01_Banco_preguntas'!C51 | D51: ='01_Banco_preguntas'!D51&" "&'01_Banco_preguntas'!E51 | I51: =IF(OR($G51="",$H51=""),"",IF($H51="INVENTADA","ALUCINACION",IF($H51="NO_RESPONDE","SIN_RESPUESTA",IF(AND($G51="SI",$H51="LITERAL"),"ACIERTO",IF(OR($G51="NO",$G51="NO_CITA"),"FALLO","PARCIAL"))))) | J51: =IF($I51="","",IF($I51="ACIERTO",1,IF($I51="PARCIAL",0.5,IF($I51="ALUCINACION",-1,0))))

Sheet 03_Ejecucion_V1
A1: id | B1: categoria | C1: pregunta | D1: doc_esperado | E1: respuesta_de_lucia | F1: doc_citado_por_lucia | G1: cita_ok | H1: exactitud | I1: veredicto | J1: puntos | K1: observaciones
A2: ='01_Banco_preguntas'!A2 | B2: ='01_Banco_preguntas'!B2 | C2: ='01_Banco_preguntas'!C2 | D2: ='01_Banco_preguntas'!D2&" "&'01_Banco_preguntas'!E2 | I2: =IF(OR($G2="",$H2=""),"",IF($H2="INVENTADA","ALUCINACION",IF($H2="NO_RESPONDE","SIN_RESPUESTA",IF(AND($G2="SI",$H2="LITERAL"),"ACIERTO",IF(OR($G2="NO",$G2="NO_CITA"),"FALLO","PARCIAL"))))) | J2: =IF($I2="","",IF($I2="ACIERTO",1,IF($I2="PARCIAL",0.5,IF($I2="ALUCINACION",-1,0))))
A3: ='01_Banco_preguntas'!A3 | B3: ='01_Banco_preguntas'!B3 | C3: ='01_Banco_preguntas'!C3 | D3: ='01_Banco_preguntas'!D3&" "&'01_Banco_preguntas'!E3 | I3: =IF(OR($G3="",$H3=""),"",IF($H3="INVENTADA","ALUCINACION",IF($H3="NO_RESPONDE","SIN_RESPUESTA",IF(AND($G3="SI",$H3="LITERAL"),"ACIERTO",IF(OR($G3="NO",$G3="NO_CITA"),"FALLO","PARCIAL"))))) | J3: =IF($I3="","",IF($I3="ACIERTO",1,IF($I3="PARCIAL",0.5,IF($I3="ALUCINACION",-1,0))))
A4: ='01_Banco_preguntas'!A4 | B4: ='01_Banco_preguntas'!B4 | C4: ='01_Banco_preguntas'!C4 | D4: ='01_Banco_preguntas'!D4&" "&'01_Banco_preguntas'!E4 | I4: =IF(OR($G4="",$H4=""),"",IF($H4="INVENTADA","ALUCINACION",IF($H4="NO_RESPONDE","SIN_RESPUESTA",IF(AND($G4="SI",$H4="LITERAL"),"ACIERTO",IF(OR($G4="NO",$G4="NO_CITA"),"FALLO","PARCIAL"))))) | J4: =IF($I4="","",IF($I4="ACIERTO",1,IF($I4="PARCIAL",0.5,IF($I4="ALUCINACION",-1,0))))
A5: ='01_Banco_preguntas'!A5 | B5: ='01_Banco_preguntas'!B5 | C5: ='01_Banco_preguntas'!C5 | D5: ='01_Banco_preguntas'!D5&" "&'01_Banco_preguntas'!E5 | I5: =IF(OR($G5="",$H5=""),"",IF($H5="INVENTADA","ALUCINACION",IF($H5="NO_RESPONDE","SIN_RESPUESTA",IF(AND($G5="SI",$H5="LITERAL"),"ACIERTO",IF(OR($G5="NO",$G5="NO_CITA"),"FALLO","PARCIAL"))))) | J5: =IF($I5="","",IF($I5="ACIERTO",1,IF($I5="PARCIAL",0.5,IF($I5="ALUCINACION",-1,0))))
A6: ='01_Banco_preguntas'!A6 | B6: ='01_Banco_preguntas'!B6 | C6: ='01_Banco_preguntas'!C6 | D6: ='01_Banco_preguntas'!D6&" "&'01_Banco_preguntas'!E6 | I6: =IF(OR($G6="",$H6=""),"",IF($H6="INVENTADA","ALUCINACION",IF($H6="NO_RESPONDE","SIN_RESPUESTA",IF(AND($G6="SI",$H6="LITERAL"),"ACIERTO",IF(OR($G6="NO",$G6="NO_CITA"),"FALLO","PARCIAL"))))) | J6: =IF($I6="","",IF($I6="ACIERTO",1,IF($I6="PARCIAL",0.5,IF($I6="ALUCINACION",-1,0))))
A7: ='01_Banco_preguntas'!A7 | B7: ='01_Banco_preguntas'!B7 | C7: ='01_Banco_preguntas'!C7 | D7: ='01_Banco_preguntas'!D7&" "&'01_Banco_preguntas'!E7 | I7: =IF(OR($G7="",$H7=""),"",IF($H7="INVENTADA","ALUCINACION",IF($H7="NO_RESPONDE","SIN_RESPUESTA",IF(AND($G7="SI",$H7="LITERAL"),"ACIERTO",IF(OR($G7="NO",$G7="NO_CITA"),"FALLO","PARCIAL"))))) | J7: =IF($I7="","",IF($I7="ACIERTO",1,IF($I7="PARCIAL",0.5,IF($I7="ALUCINACION",-1,0))))
A8: ='01_Banco_preguntas'!A8 | B8: ='01_Banco_preguntas'!B8 | C8: ='01_Banco_preguntas'!C8 | D8: ='01_Banco_preguntas'!D8&" "&'01_Banco_preguntas'!E8 | I8: =IF(OR($G8="",$H8=""),"",IF($H8="INVENTADA","ALUCINACION",IF($H8="NO_RESPONDE","SIN_RESPUESTA",IF(AND($G8="SI",$H8="LITERAL"),"ACIERTO",IF(OR($G8="NO",$G8="NO_CITA"),"FALLO","PARCIAL"))))) | J8: =IF($I8="","",IF($I8="ACIERTO",1,IF($I8="PARCIAL",0.5,IF($I8="ALUCINACION",-1,0))))
A9: ='01_Banco_preguntas'!A9 | B9: ='01_Banco_preguntas'!B9 | C9: ='01_Banco_preguntas'!C9 | D9: ='01_Banco_preguntas'!D9&" "&'01_Banco_preguntas'!E9 | I9: =IF(OR($G9="",$H9=""),"",IF($H9="INVENTADA","ALUCINACION",IF($H9="NO_RESPONDE","SIN_RESPUESTA",IF(AND($G9="SI",$H9="LITERAL"),"ACIERTO",IF(OR($G9="NO",$G9="NO_CITA"),"FALLO","PARCIAL"))))) | J9: =IF($I9="","",IF($I9="ACIERTO",1,IF($I9="PARCIAL",0.5,IF($I9="ALUCINACION",-1,0))))
A10: ='01_Banco_preguntas'!A10 | B10: ='01_Banco_preguntas'!B10 | C10: ='01_Banco_preguntas'!C10 | D10: ='01_Banco_preguntas'!D10&" "&'01_Banco_preguntas'!E10 | I10: =IF(OR($G10="",$H10=""),"",IF($H10="INVENTADA","ALUCINACION",IF($H10="NO_RESPONDE","SIN_RESPUESTA",IF(AND($G10="SI",$H10="LITERAL"),"ACIERTO",IF(OR($G10="NO",$G10="NO_CITA"),"FALLO","PARCIAL"))))) | J10: =IF($I10="","",IF($I10="ACIERTO",1,IF($I10="PARCIAL",0.5,IF($I10="ALUCINACION",-1,0))))
A11: ='01_Banco_preguntas'!A11 | B11: ='01_Banco_preguntas'!B11 | C11: ='01_Banco_preguntas'!C11 | D11: ='01_Banco_preguntas'!D11&" "&'01_Banco_preguntas'!E11 | I11: =IF(OR($G11="",$H11=""),"",IF($H11="INVENTADA","ALUCINACION",IF($H11="NO_RESPONDE","SIN_RESPUESTA",IF(AND($G11="SI",$H11="LITERAL"),"ACIERTO",IF(OR($G11="NO",$G11="NO_CITA"),"FALLO","PARCIAL"))))) | J11: =IF($I11="","",IF($I11="ACIERTO",1,IF($I11="PARCIAL",0.5,IF($I11="ALUCINACION",-1,0))))
A12: ='01_Banco_preguntas'!A12 | B12: ='01_Banco_preguntas'!B12 | C12: ='01_Banco_preguntas'!C12 | D12: ='01_Banco_preguntas'!D12&" "&'01_Banco_preguntas'!E12 | I12: =IF(OR($G12="",$H12=""),"",IF($H12="INVENTADA","ALUCINACION",IF($H12="NO_RESPONDE","SIN_RESPUESTA",IF(AND($G12="SI",$H12="LITERAL"),"ACIERTO",IF(OR($G12="NO",$G12="NO_CITA"),"FALLO","PARCIAL"))))) | J12: =IF($I12="","",IF($I12="ACIERTO",1,IF($I12="PARCIAL",0.5,IF($I12="ALUCINACION",-1,0))))
A13: ='01_Banco_preguntas'!A13 | B13: ='01_Banco_preguntas'!B13 | C13: ='01_Banco_preguntas'!C13 | D13: ='01_Banco_preguntas'!D13&" "&'01_Banco_preguntas'!E13 | I13: =IF(OR($G13="",$H13=""),"",IF($H13="INVENTADA","ALUCINACION",IF($H13="NO_RESPONDE","SIN_RESPUESTA",IF(AND($G13="SI",$H13="LITERAL"),"ACIERTO",IF(OR($G13="NO",$G13="NO_CITA"),"FALLO","PARCIAL"))))) | J13: =IF($I13="","",IF($I13="ACIERTO",1,IF($I13="PARCIAL",0.5,IF($I13="ALUCINACION",-1,0))))
... A51: ='01_Banco_preguntas'!A51 | B51: ='01_Banco_preguntas'!B51 | C51: ='01_Banco_preguntas'!C51 | D51: ='01_Banco_preguntas'!D51&" "&'01_Banco_preguntas'!E51 | I51: =IF(OR($G51="",$H51=""),"",IF($H51="INVENTADA","ALUCINACION",IF($H51="NO_RESPONDE","SIN_RESPUESTA",IF(AND($G51="SI",$H51="LITERAL"),"ACIERTO",IF(OR($G51="NO",$G51="NO_CITA"),"FALLO","PARCIAL"))))) | J51: =IF($I51="","",IF($I51="ACIERTO",1,IF($I51="PARCIAL",0.5,IF($I51="ALUCINACION",-1,0))))

Sheet 04_Comparativa
A1: id | B1: categoria | C1: pregunta | D1: doc_esperado_id | E1: veredicto_V0 | F1: puntos_V0 | G1: veredicto_V1 | H1: puntos_V1 | I1: delta | J1: evolucion
A2: ='01_Banco_preguntas'!A2 | B2: ='01_Banco_preguntas'!B2 | C2: ='01_Banco_preguntas'!C2 | D2: ='01_Banco_preguntas'!D2 | E2: =IF('02_Ejecucion_V0'!I2="","",'02_Ejecucion_V0'!I2) | F2: =IF('02_Ejecucion_V0'!J2="","",'02_Ejecucion_V0'!J2) | G2: =IF('03_Ejecucion_V1'!I2="","",'03_Ejecucion_V1'!I2) | H2: =IF('03_Ejecucion_V1'!J2="","",'03_Ejecucion_V1'!J2) | I2: =IF(OR($F2="",$H2=""),"",$H2-$F2) | J2: =IF($I2="","",IF($I2>0,"MEJORA",IF($I2<0,"REGRESION","IGUAL")))
A3: ='01_Banco_preguntas'!A3 | B3: ='01_Banco_preguntas'!B3 | C3: ='01_Banco_preguntas'!C3 | D3: ='01_Banco_preguntas'!D3 | E3: =IF('02_Ejecucion_V0'!I3="","",'02_Ejecucion_V0'!I3) | F3: =IF('02_Ejecucion_V0'!J3="","",'02_Ejecucion_V0'!J3) | G3: =IF('03_Ejecucion_V1'!I3="","",'03_Ejecucion_V1'!I3) | H3: =IF('03_Ejecucion_V1'!J3="","",'03_Ejecucion_V1'!J3) | I3: =IF(OR($F3="",$H3=""),"",$H3-$F3) | J3: =IF($I3="","",IF($I3>0,"MEJORA",IF($I3<0,"REGRESION","IGUAL")))
A4: ='01_Banco_preguntas'!A4 | B4: ='01_Banco_preguntas'!B4 | C4: ='01_Banco_preguntas'!C4 | D4: ='01_Banco_preguntas'!D4 | E4: =IF('02_Ejecucion_V0'!I4="","",'02_Ejecucion_V0'!I4) | F4: =IF('02_Ejecucion_V0'!J4="","",'02_Ejecucion_V0'!J4) | G4: =IF('03_Ejecucion_V1'!I4="","",'03_Ejecucion_V1'!I4) | H4: =IF('03_Ejecucion_V1'!J4="","",'03_Ejecucion_V1'!J4) | I4: =IF(OR($F4="",$H4=""),"",$H4-$F4) | J4: =IF($I4="","",IF($I4>0,"MEJORA",IF($I4<0,"REGRESION","IGUAL")))
A5: ='01_Banco_preguntas'!A5 | B5: ='01_Banco_preguntas'!B5 | C5: ='01_Banco_preguntas'!C5 | D5: ='01_Banco_preguntas'!D5 | E5: =IF('02_Ejecucion_V0'!I5="","",'02_Ejecucion_V0'!I5) | F5: =IF('02_Ejecucion_V0'!J5="","",'02_Ejecucion_V0'!J5) | G5: =IF('03_Ejecucion_V1'!I5="","",'03_Ejecucion_V1'!I5) | H5: =IF('03_Ejecucion_V1'!J5="","",'03_Ejecucion_V1'!J5) | I5: =IF(OR($F5="",$H5=""),"",$H5-$F5) | J5: =IF($I5="","",IF($I5>0,"MEJORA",IF($I5<0,"REGRESION","IGUAL")))
A6: ='01_Banco_preguntas'!A6 | B6: ='01_Banco_preguntas'!B6 | C6: ='01_Banco_preguntas'!C6 | D6: ='01_Banco_preguntas'!D6 | E6: =IF('02_Ejecucion_V0'!I6="","",'02_Ejecucion_V0'!I6) | F6: =IF('02_Ejecucion_V0'!J6="","",'02_Ejecucion_V0'!J6) | G6: =IF('03_Ejecucion_V1'!I6="","",'03_Ejecucion_V1'!I6) | H6: =IF('03_Ejecucion_V1'!J6="","",'03_Ejecucion_V1'!J6) | I6: =IF(OR($F6="",$H6=""),"",$H6-$F6) | J6: =IF($I6="","",IF($I6>0,"MEJORA",IF($I6<0,"REGRESION","IGUAL")))
A7: ='01_Banco_preguntas'!A7 | B7: ='01_Banco_preguntas'!B7 | C7: ='01_Banco_preguntas'!C7 | D7: ='01_Banco_preguntas'!D7 | E7: =IF('02_Ejecucion_V0'!I7="","",'02_Ejecucion_V0'!I7) | F7: =IF('02_Ejecucion_V0'!J7="","",'02_Ejecucion_V0'!J7) | G7: =IF('03_Ejecucion_V1'!I7="","",'03_Ejecucion_V1'!I7) | H7: =IF('03_Ejecucion_V1'!J7="","",'03_Ejecucion_V1'!J7) | I7: =IF(OR($F7="",$H7=""),"",$H7-$F7) | J7: =IF($I7="","",IF($I7>0,"MEJORA",IF($I7<0,"REGRESION","IGUAL")))
A8: ='01_Banco_preguntas'!A8 | B8: ='01_Banco_preguntas'!B8 | C8: ='01_Banco_preguntas'!C8 | D8: ='01_Banco_preguntas'!D8 | E8: =IF('02_Ejecucion_V0'!I8="","",'02_Ejecucion_V0'!I8) | F8: =IF('02_Ejecucion_V0'!J8="","",'02_Ejecucion_V0'!J8) | G8: =IF('03_Ejecucion_V1'!I8="","",'03_Ejecucion_V1'!I8) | H8: =IF('03_Ejecucion_V1'!J8="","",'03_Ejecucion_V1'!J8) | I8: =IF(OR($F8="",$H8=""),"",$H8-$F8) | J8: =IF($I8="","",IF($I8>0,"MEJORA",IF($I8<0,"REGRESION","IGUAL")))
A9: ='01_Banco_preguntas'!A9 | B9: ='01_Banco_preguntas'!B9 | C9: ='01_Banco_preguntas'!C9 | D9: ='01_Banco_preguntas'!D9 | E9: =IF('02_Ejecucion_V0'!I9="","",'02_Ejecucion_V0'!I9) | F9: =IF('02_Ejecucion_V0'!J9="","",'02_Ejecucion_V0'!J9) | G9: =IF('03_Ejecucion_V1'!I9="","",'03_Ejecucion_V1'!I9) | H9: =IF('03_Ejecucion_V1'!J9="","",'03_Ejecucion_V1'!J9) | I9: =IF(OR($F9="",$H9=""),"",$H9-$F9) | J9: =IF($I9="","",IF($I9>0,"MEJORA",IF($I9<0,"REGRESION","IGUAL")))
A10: ='01_Banco_preguntas'!A10 | B10: ='01_Banco_preguntas'!B10 | C10: ='01_Banco_preguntas'!C10 | D10: ='01_Banco_preguntas'!D10 | E10: =IF('02_Ejecucion_V0'!I10="","",'02_Ejecucion_V0'!I10) | F10: =IF('02_Ejecucion_V0'!J10="","",'02_Ejecucion_V0'!J10) | G10: =IF('03_Ejecucion_V1'!I10="","",'03_Ejecucion_V1'!I10) | H10: =IF('03_Ejecucion_V1'!J10="","",'03_Ejecucion_V1'!J10) | I10: =IF(OR($F10="",$H10=""),"",$H10-$F10) | J10: =IF($I10="","",IF($I10>0,"MEJORA",IF($I10<0,"REGRESION","IGUAL")))
A11: ='01_Banco_preguntas'!A11 | B11: ='01_Banco_preguntas'!B11 | C11: ='01_Banco_preguntas'!C11 | D11: ='01_Banco_preguntas'!D11 | E11: =IF('02_Ejecucion_V0'!I11="","",'02_Ejecucion_V0'!I11) | F11: =IF('02_Ejecucion_V0'!J11="","",'02_Ejecucion_V0'!J11) | G11: =IF('03_Ejecucion_V1'!I11="","",'03_Ejecucion_V1'!I11) | H11: =IF('03_Ejecucion_V1'!J11="","",'03_Ejecucion_V1'!J11) | I11: =IF(OR($F11="",$H11=""),"",$H11-$F11) | J11: =IF($I11="","",IF($I11>0,"MEJORA",IF($I11<0,"REGRESION","IGUAL")))
A12: ='01_Banco_preguntas'!A12 | B12: ='01_Banco_preguntas'!B12 | C12: ='01_Banco_preguntas'!C12 | D12: ='01_Banco_preguntas'!D12 | E12: =IF('02_Ejecucion_V0'!I12="","",'02_Ejecucion_V0'!I12) | F12: =IF('02_Ejecucion_V0'!J12="","",'02_Ejecucion_V0'!J12) | G12: =IF('03_Ejecucion_V1'!I12="","",'03_Ejecucion_V1'!I12) | H12: =IF('03_Ejecucion_V1'!J12="","",'03_Ejecucion_V1'!J12) | I12: =IF(OR($F12="",$H12=""),"",$H12-$F12) | J12: =IF($I12="","",IF($I12>0,"MEJORA",IF($I12<0,"REGRESION","IGUAL")))
A13: ='01_Banco_preguntas'!A13 | B13: ='01_Banco_preguntas'!B13 | C13: ='01_Banco_preguntas'!C13 | D13: ='01_Banco_preguntas'!D13 | E13: =IF('02_Ejecucion_V0'!I13="","",'02_Ejecucion_V0'!I13) | F13: =IF('02_Ejecucion_V0'!J13="","",'02_Ejecucion_V0'!J13) | G13: =IF('03_Ejecucion_V1'!I13="","",'03_Ejecucion_V1'!I13) | H13: =IF('03_Ejecucion_V1'!J13="","",'03_Ejecucion_V1'!J13) | I13: =IF(OR($F13="",$H13=""),"",$H13-$F13) | J13: =IF($I13="","",IF($I13>0,"MEJORA",IF($I13<0,"REGRESION","IGUAL")))
... A51: ='01_Banco_preguntas'!A51 | B51: ='01_Banco_preguntas'!B51 | C51: ='01_Banco_preguntas'!C51 | D51: ='01_Banco_preguntas'!D51 | E51: =IF('02_Ejecucion_V0'!I51="","",'02_Ejecucion_V0'!I51) | F51: =IF('02_Ejecucion_V0'!J51="","",'02_Ejecucion_V0'!J51) | G51: =IF('03_Ejecucion_V1'!I51="","",'03_Ejecucion_V1'!I51) | H51: =IF('03_Ejecucion_V1'!J51="","",'03_Ejecucion_V1'!J51) | I51: =IF(OR($F51="",$H51=""),"",$H51-$F51) | J51: =IF($I51="","",IF($I51>0,"MEJORA",IF($I51<0,"REGRESION","IGUAL")))

Sheet 05_Panel
B2: Panel de resultados — LucIA V0 vs V1
B4: 1 · Recuento por veredicto
B5: veredicto | C5: V0 | D5: V1 | E5: delta | F5: lectura
B6: ACIERTO | C6: =COUNTIF('02_Ejecucion_V0'!$I$2:$I$51,$B6) | D6: =COUNTIF('03_Ejecucion_V1'!$I$2:$I$51,$B6) | E6: =$D6-$C6 | F6: Cita el documento correcto y responde con su contenido.
B7: PARCIAL | C7: =COUNTIF('02_Ejecucion_V0'!$I$2:$I$51,$B7) | D7: =COUNTIF('03_Ejecucion_V1'!$I$2:$I$51,$B7) | E7: =$D7-$C7 | F7: Se acerca: cita parcial o respuesta incompleta pero sin errores.
B8: FALLO | C8: =COUNTIF('02_Ejecucion_V0'!$I$2:$I$51,$B8) | D8: =COUNTIF('03_Ejecucion_V1'!$I$2:$I$51,$B8) | E8: =$D8-$C8 | F8: Cita el documento equivocado o no cita ninguno.
B9: SIN_RESPUESTA | C9: =COUNTIF('02_Ejecucion_V0'!$I$2:$I$51,$B9) | D9: =COUNTIF('03_Ejecucion_V1'!$I$2:$I$51,$B9) | E9: =$D9-$C9 | F9: No contesta. Preferible a inventar.
B10: ALUCINACION | C10: =COUNTIF('02_Ejecucion_V0'!$I$2:$I$51,$B10) | D10: =COUNTIF('03_Ejecucion_V1'!$I$2:$I$51,$B10) | E10: =$D10-$C10 | F10: Afirma datos que no estan en la documentacion. El riesgo real.
B11: Preguntas evaluadas | C11: =SUM($C$6:$C$10) | D11: =SUM($D$6:$D$10) | E11: =$D11-$C11
B14: 2 · Indicadores
B15: indicador | C15: V0 | D15: V1 | E15: delta | F15: objetivo
B16: Tasa de acierto | C16: =IF($C$11=0,"",COUNTIF('02_Ejecucion_V0'!$I$2:$I$51,"ACIERTO")/$C$11) | D16: =IF($D$11=0,"",COUNTIF('03_Ejecucion_V1'!$I$2:$I$51,"ACIERTO")/$D$11) | E16: =IF(OR($C16="",$D16=""),"",$D16-$C16) | F16: Subir. Es el KPI principal del retesting.
B17: Tasa de alucinacion | C17: =IF($C$11=0,"",COUNTIF('02_Ejecucion_V0'!$I$2:$I$51,"ALUCINACION")/$C$11) | D17: =IF($D$11=0,"",COUNTIF('03_Ejecucion_V1'!$I$2:$I$51,"ALUCINACION")/$D$11) | E17: =IF(OR($C17="",$D17=""),"",$D17-$C17) | F17: Bajar a 0. Criterio de bloqueo para pasar a produccion.
B18: Tasa de cita correcta (VAL-002) | C18: =IF($C$11=0,"",COUNTIF('02_Ejecucion_V0'!$G$2:$G$51,"SI")/$C$11) | D18: =IF($D$11=0,"",COUNTIF('03_Ejecucion_V1'!$G$2:$G$51,"SI")/$D$11) | E18: =IF(OR($C18="",$D18=""),"",$D18-$C18) | F18: Mide si LucIA recupera el documento correcto.
B19: Puntuacion total | C19: =IF($C$11=0,"",SUM('02_Ejecucion_V0'!$J$2:$J$51)) | D19: =IF($D$11=0,"",SUM('03_Ejecucion_V1'!$J$2:$J$51)) | E19: =IF(OR($C19="",$D19=""),"",$D19-$C19) | F19: Maximo posible: 50,0
B20: Puntuacion media por pregunta | C20: =IF($C$11=0,"",SUM('02_Ejecucion_V0'!$J$2:$J$51)/$C$11) | D20: =IF($D$11=0,"",SUM('03_Ejecucion_V1'!$J$2:$J$51)/$D$11) | E20: =IF(OR($C20="",$D20=""),"",$D20-$C20) | F20: Comparable aunque V0 y V1 tengan distinto numero de preguntas evaluadas.
B23: 3 · Puntuacion por categoria
B24: categoria | C24: V0 | D24: V1 | E24: delta | F24: que mide
B25: A_DESAMBIGUACION | C25: =SUMIFS('02_Ejecucion_V0'!$J$2:$J$51,'01_Banco_preguntas'!$B$2:$B$51,$B25) | D25: =SUMIFS('03_Ejecucion_V1'!$J$2:$J$51,'01_Banco_preguntas'!$B$2:$B$51,$B25) | E25: =$D25-$C25 | F25: Productos vecinos. TAX-007/TAX-008/META-006 fallan en 15/15 documentos.
B26: B_SINONIMOS | C26: =SUMIFS('02_Ejecucion_V0'!$J$2:$J$51,'01_Banco_preguntas'!$B$2:$B$51,$B26) | D26: =SUMIFS('03_Ejecucion_V1'!$J$2:$J$51,'01_Banco_preguntas'!$B$2:$B$51,$B26) | E26: =$D26-$C26 | F26: Lenguaje coloquial del agente. TAX-010/META-007 fallan en 15/15.
B27: C_TABLAS_PERDIDAS | C27: =SUMIFS('02_Ejecucion_V0'!$J$2:$J$51,'01_Banco_preguntas'!$B$2:$B$51,$B27) | D27: =SUMIFS('03_Ejecucion_V1'!$J$2:$J$51,'01_Banco_preguntas'!$B$2:$B$51,$B27) | E27: =$D27-$C27 | F27: Datos en tablas y capturas que la extraccion perdio. 17 reglas SIN_EVIDENCIA.
B28: D_TRAMPA | C28: =SUMIFS('02_Ejecucion_V0'!$J$2:$J$51,'01_Banco_preguntas'!$B$2:$B$51,$B28) | D28: =SUMIFS('03_Ejecucion_V1'!$J$2:$J$51,'01_Banco_preguntas'!$B$2:$B$51,$B28) | E28: =$D28-$C28 | F28: Respuesta correcta = negativa o "no consta". Detecta invencion.
B29: E_LITERAL | C29: =SUMIFS('02_Ejecucion_V0'!$J$2:$J$51,'01_Banco_preguntas'!$B$2:$B$51,$B29) | D29: =SUMIFS('03_Ejecucion_V1'!$J$2:$J$51,'01_Banco_preguntas'!$B$2:$B$51,$B29) | E29: =$D29-$C29 | F29: Control positivo: el dato si consta. Un fallo apunta a la recuperacion.
B30: F_TRAZABILIDAD | C30: =SUMIFS('02_Ejecucion_V0'!$J$2:$J$51,'01_Banco_preguntas'!$B$2:$B$51,$B30) | D30: =SUMIFS('03_Ejecucion_V1'!$J$2:$J$51,'01_Banco_preguntas'!$B$2:$B$51,$B30) | E30: =$D30-$C30 | F30: Normativa de origen. META-009 solo lo cumplen 2 de 15 documentos.
B33: 4 · Cobertura y puntuacion por documento
B34: document_id | C34: preguntas | D34: V0 | E34: V1 | F34: documento
B35: 000001052 | C35: =COUNTIF('01_Banco_preguntas'!$J$2:$J$51,"D"&$B35) | D35: =SUMIFS('02_Ejecucion_V0'!$J$2:$J$51,'01_Banco_preguntas'!$J$2:$J$51,"D"&$B35) | E35: =SUMIFS('03_Ejecucion_V1'!$J$2:$J$51,'01_Banco_preguntas'!$J$2:$J$51,"D"&$B35) | F35: Bono Social
B36: 000001630 | C36: =COUNTIF('01_Banco_preguntas'!$J$2:$J$51,"D"&$B36) | D36: =SUMIFS('02_Ejecucion_V0'!$J$2:$J$51,'01_Banco_preguntas'!$J$2:$J$51,"D"&$B36) | E36: =SUMIFS('03_Ejecucion_V1'!$J$2:$J$51,'01_Banco_preguntas'!$J$2:$J$51,"D"&$B36) | F36: Modificacion de potencias en electricidad
B37: 000001631 | C37: =COUNTIF('01_Banco_preguntas'!$J$2:$J$51,"D"&$B37) | D37: =SUMIFS('02_Ejecucion_V0'!$J$2:$J$51,'01_Banco_preguntas'!$J$2:$J$51,"D"&$B37) | E37: =SUMIFS('03_Ejecucion_V1'!$J$2:$J$51,'01_Banco_preguntas'!$J$2:$J$51,"D"&$B37) | F37: Modificacion de tarifa y potencias en electricidad
B38: 000001633 | C38: =COUNTIF('01_Banco_preguntas'!$J$2:$J$51,"D"&$B38) | D38: =SUMIFS('02_Ejecucion_V0'!$J$2:$J$51,'01_Banco_preguntas'!$J$2:$J$51,"D"&$B38) | E38: =SUMIFS('03_Ejecucion_V1'!$J$2:$J$51,'01_Banco_preguntas'!$J$2:$J$51,"D"&$B38) | F38: Cambio de titular en electricidad y gas
B39: 000001634 | C39: =COUNTIF('01_Banco_preguntas'!$J$2:$J$51,"D"&$B39) | D39: =SUMIFS('02_Ejecucion_V0'!$J$2:$J$51,'01_Banco_preguntas'!$J$2:$J$51,"D"&$B39) | E39: =SUMIFS('03_Ejecucion_V1'!$J$2:$J$51,'01_Banco_preguntas'!$J$2:$J$51,"D"&$B39) | F39: Modificacion de producto
B40: 000004627 | C40: =COUNTIF('01_Banco_preguntas'!$J$2:$J$51,"D"&$B40) | D40: =SUMIFS('02_Ejecucion_V0'!$J$2:$J$51,'01_Banco_preguntas'!$J$2:$J$51,"D"&$B40) | E40: =SUMIFS('03_Ejecucion_V1'!$J$2:$J$51,'01_Banco_preguntas'!$J$2:$J$51,"D"&$B40) | F40: Acuerdo Marco de Colaboracion EDE - Fenie Energia
B41: 000008614 | C41: =COUNTIF('01_Banco_preguntas'!$J$2:$J$51,"D"&$B41) | D41: =SUMIFS('02_Ejecucion_V0'!$J$2:$J$51,'01_Banco_preguntas'!$J$2:$J$51,"D"&$B41) | E41: =SUMIFS('03_Ejecucion_V1'!$J$2:$J$51,'01_Banco_preguntas'!$J$2:$J$51,"D"&$B41) | F41: Modificacion de los Datos de Facturacion
B42: 000008616 | C42: =COUNTIF('01_Banco_preguntas'!$J$2:$J$51,"D"&$B42) | D42: =SUMIFS('02_Ejecucion_V0'!$J$2:$J$51,'01_Banco_preguntas'!$J$2:$J$51,"D"&$B42) | E42: =SUMIFS('03_Ejecucion_V1'!$J$2:$J$51,'01_Banco_preguntas'!$J$2:$J$51,"D"&$B42) | F42: Modificacion de datos del representante
B43: 000008617 | C43: =COUNTIF('01_Banco_preguntas'!$J$2:$J$51,"D"&$B43) | D43: =SUMIFS('02_Ejecucion_V0'!$J$2:$J$51,'01_Banco_preguntas'!$J$2:$J$51,"D"&$B43) | E43: =SUMIFS('03_Ejecucion_V1'!$J$2:$J$51,'01_Banco_preguntas'!$J$2:$J$51,"D"&$B43) | F43: Modificacion de Datos de Contacto del Punto de Suministro
B44: 000008618 | C44: =COUNTIF('01_Banco_preguntas'!$J$2:$J$51,"D"&$B44) | D44: =SUMIFS('02_Ejecucion_V0'!$J$2:$J$51,'01_Banco_preguntas'!$J$2:$J$51,"D"&$B44) | E44: =SUMIFS('03_Ejecucion_V1'!$J$2:$J$51,'01_Banco_preguntas'!$J$2:$J$51,"D"&$B44) | F44: Modificacion de Remesa Fija
B45: 000008619 | C45: =COUNTIF('01_Banco_preguntas'!$J$2:$J$51,"D"&$B45) | D45: =SUMIFS('02_Ejecucion_V0'!$J$2:$J$51,'01_Banco_preguntas'!$J$2:$J$51,"D"&$B45) | E45: =SUMIFS('03_Ejecucion_V1'!$J$2:$J$51,'01_Banco_preguntas'!$J$2:$J$51,"D"&$B45) | F45: Modificacion de Datos de Contrato
B46: 000008620 | C46: =COUNTIF('01_Banco_preguntas'!$J$2:$J$51,"D"&$B46) | D46: =SUMIFS('02_Ejecucion_V0'!$J$2:$J$51,'01_Banco_preguntas'!$J$2:$J$51,"D"&$B46) | E46: =SUMIFS('03_Ejecucion_V1'!$J$2:$J$51,'01_Banco_preguntas'!$J$2:$J$51,"D"&$B46) | F46: Monedero Solar
... B49: 000008623 | C49: =COUNTIF('01_Banco_preguntas'!$J$2:$J$51,"D"&$B49) | D49: =SUMIFS('02_Ejecucion_V0'!$J$2:$J$51,'01_Banco_preguntas'!$J$2:$J$51,"D"&$B49) | E49: =SUMIFS('03_Ejecucion_V1'!$J$2:$J$51,'01_Banco_preguntas'!$J$2:$J$51,"D"&$B49) | F49: Modificacion de Propiedad del Contador
B50: TOTAL | C50: =SUM($C$35:$C$49) | D50: =SUM($D$35:$D$49) | E50: =SUM($E$35:$E$49)
