Workbook

Sheet 00_Resumen
B2: Solapamiento entre los 4 documentos de modificaciones
B4: Documentos analizados
A5: clave | B5: documento | C5: tipo | D5: extension
A6: 6292 | B6: 000006292 Procedimiento para realizar modificaciones tecnicas | C6: Procedimiento | D6: 2 pag
A7: 6601 | B7: 000006601 Modificaciones administrativas | C7: Procedimiento | D7: 4 pag
A8: FAQ-ADM | B8: FAQs MODIFICACIONES ADMINISTRATIVAS (plantilla FE) | C8: FAQ | D8: 6 pag
A9: FAQ-CON | B9: 20260414 FAQs Modificaciones de contrato (plantilla fenie) | C9: FAQ | D9: 4 pag
B11: Hallazgos
B12: Temas analizados | C12: =COUNTA('01_Matriz_temas'!$A$2:$A$27)
B13: Temas presentes en 2 o mas documentos | C13: =COUNTIF('01_Matriz_temas'!$G$2:$G$27,">=2")
B14: Temas presentes en 3 o mas documentos | C14: =COUNTIF('01_Matriz_temas'!$G$2:$G$27,">=3")
B15: Temas en un solo documento | C15: =COUNTIF('01_Matriz_temas'!$G$2:$G$27,1)
B16: Contradicciones detectadas | C16: =COUNTA('03_Contradicciones'!$A$2:$A$9)
B17: De ellas, de riesgo ALTA | C17: =COUNTIF('03_Contradicciones'!$B$2:$B$9,"ALTA")
B18: Datos u avisos que un documento tiene y otro OMITE | C18: =COUNTIF('01_Matriz_temas'!$B$2:$F$27,"OMITE")
B20: El solapamiento es semantico, no copia-pega | C20: Entre los cuatro documentos NO hay una sola coincidencia literal de 9 palabras seguidas. Bajando a 5 palabras aparecen 20 pasajes entre 000006601 y el FAQs administrativo, y poco mas. Son parafrasis del mismo contenido. Consecuencia: no se puede detectar el duplicado comparando textos ni por hash, hay que hacerlo por tema.
B21: 000006601 y el FAQs administrativo son el mismo documento escrito dos veces | C21: 11 de los 12 temas administrativos estan en los dos. El unico que no se solapa en todo el conjunto es Propiedad del contador.
B22: Gana el compendio, y es el que tiene la informacion incompleta | C22: El FAQs administrativo se lleva 14 de los primeros puestos de recuperacion medidos. Gana porque cada seccion lleva un bloque "Ejemplo:" con lenguaje coloquial de agente, que casa con lo que el agente escribe. Pero es el que omite la restriccion del telefono espanol, la del producto de precio fijo, la opcion de firma en papel y el metodo de pago por codigo de barras.
B23: Cada documento tiene una mitad de la verdad | C23: El aviso de que al desactivar el Monedero Solar se pierde el saldo solo esta en el FAQs. La restriccion del telefono espanol solo esta en 000006601. Lo que recibe el agente depende de cual gane el ranking ese dia.

Sheet 01_Matriz_temas
A1: Tema | B1: 6292 TECNICAS | C1: 6601 ADMIN | D1: FAQ-ADM | E1: FAQ-CON | F1: Nota | G1: N docs
A2: Modificar producto | C2: Sec.1 | D2: Sec.1 | E2: Sec.2 y 3 | F2: Tres fuentes para el mismo tramite | G2: =COUNTA($B2:$E2)-COUNTIF($B2:$E2,"OMITE")
A3: Producto de precio fijo NO se puede modificar | C3: Sec.1 | D3: OMITE | E3: Sec.3 | F3: Restriccion critica ausente en el compendio que mas se recupera | G3: =COUNTA($B3:$E3)-COUNTIF($B3:$E3,"OMITE")
A4: Datos de cliente | C4: Sec.2 | D4: Sec.2 | E4: Sec.4 (lista) | G4: =COUNTA($B4:$E4)-COUNTIF($B4:$E4,"OMITE")
A5: Representante | C5: Sec.3 | D5: Sec.3 | E5: Sec.4 (lista) | G5: =COUNTA($B5:$E5)-COUNTIF($B5:$E5,"OMITE")
A6: Autorizado | C6: Sec.4 | D6: Sec.4 | E6: Sec.4 (lista) | G6: =COUNTA($B6:$E6)-COUNTIF($B6:$E6,"OMITE")
A7: Datos de Contacto del PS | C7: Sec.5 | D7: Sec.5 | E7: Sec.4 (lista) | G7: =COUNTA($B7:$E7)-COUNTIF($B7:$E7,"OMITE")
A8: Contacto PS: solo telefono espanol (+34) | C8: Sec.5 | D8: OMITE | F8: Restriccion ausente en el compendio. Nuestra pregunta E04 solo acerto porque gano 6601 | G8: =COUNTA($B8:$E8)-COUNTIF($B8:$E8,"OMITE")
A9: Correo de facturacion | C9: Sec.6.4 | D9: Sec.6 | G9: =COUNTA($B9:$E9)-COUNTIF($B9:$E9,"OMITE")
A10: Cuenta bancaria | C10: Sec.6.2 | D10: Sec.7 | E10: Sec.7 (masiva) | F10: Tres fuentes | G10: =COUNTA($B10:$E10)-COUNTIF($B10:$E10,"OMITE")
A11: Direccion de facturacion | C11: Sec.6.3 | D11: Sec.8 | F11: Pasos CONTRADICTORIOS: ver hoja 03 | G11: =COUNTA($B11:$E11)-COUNTIF($B11:$E11,"OMITE")
A12: Metodo de pago codigo de barras | C12: Sec.6.1 | D12: OMITE | G12: =COUNTA($B12:$E12)-COUNTIF($B12:$E12,"OMITE")
A13: Datos del contrato | B13: Lo menciona | C13: Sec.7 | D13: Sec.9 | E13: Sec.4 (lista) | F13: Cuatro fuentes. 6292 admite que es administrativa y aun asi la incluye | G13: =COUNTA($B13:$E13)-COUNTIF($B13:$E13,"OMITE")
A14: Tipo de firma: opcion PAPEL | C14: Sec.7 | D14: OMITE | F14: FAQ-ADM solo dice Distancia o Presencial | G14: =COUNTA($B14:$E14)-COUNTIF($B14:$E14,"OMITE")
A15: Remesa fija | C15: Sec.8 | D15: Sec.10 | E15: Sec.4 (lista) | G15: =COUNTA($B15:$E15)-COUNTIF($B15:$E15,"OMITE")
A16: Remesa fija: coste | C16: Sec.8 | D16: Sec.10 | F16: Los dos coinciden: 1% fijo / 1,2 EUR-MWh o 1,6 EUR-mes | G16: =COUNTA($B16:$E16)-COUNTIF($B16:$E16,"OMITE")
A17: Monedero Solar | B17: Sec.1 lo menciona | C17: Sec.9 | D17: Sec.11 | E17: Sec.4 (lista) | F17: CUATRO fuentes | G17: =COUNTA($B17:$E17)-COUNTIF($B17:$E17,"OMITE")
A18: Monedero Solar: al desactivar se pierde el saldo | C18: OMITE | D18: Sec.11 | F18: Aviso critico solo en el compendio. El procedimiento oficial solo dice: puede desactivarse, si | G18: =COUNTA($B18:$E18)-COUNTIF($B18:$E18,"OMITE")
A19: Autoconsumo | B19: Sec.1 | E19: Sec.9 | G19: =COUNTA($B19:$E19)-COUNTIF($B19:$E19,"OMITE")
A20: Tarifa / Tension / Potencias | B20: Sec.2 | E20: Sec.4 (lista) | G20: =COUNTA($B20:$E20)-COUNTIF($B20:$E20,"OMITE")
A21: Maximetro | B21: Sec.3 | E21: Sec.4 y 10 | G21: =COUNTA($B21:$E21)-COUNTIF($B21:$E21,"OMITE")
A22: Maximetro: potencia segun CIE/boletin | B22: Sec.3 | E22: Sec.10 | F22: Tambien en 000006590 pag.13, casi palabra por palabra. TRES documentos con la misma regla | G22: =COUNTA($B22:$E22)-COUNTIF($B22:$E22,"OMITE")
A23: Propiedad del contador | B23: Sec.4 | F23: Unico tema sin solapar | G23: =COUNTA($B23:$E23)-COUNTIF($B23:$E23,"OMITE")
A24: Cambio de titular con modificaciones | E24: Sec.1 | G24: =COUNTA($B24:$E24)-COUNTIF($B24:$E24,"OMITE")
A25: Baja de contrato / bajas temporales | E25: Sec.5 y 6 | G25: =COUNTA($B25:$E25)-COUNTIF($B25:$E25,"OMITE")
A26: Modificaciones simultaneas | C26: Intro | E26: Sec.11 | F26: CONTRADICCION directa: ver hoja 03 | G26: =COUNTA($B26:$E26)-COUNTIF($B26:$E26,"OMITE")
A27: Modificacion con renovacion en curso | E27: Sec.4 y 11 | G27: =COUNTA($B27:$E27)-COUNTIF($B27:$E27,"OMITE")

Sheet 02_Coincidencias_literales
A1: Pasajes de 5-6 palabras compartidos. No hay ninguna coincidencia de 9 palabras: el solapamiento es de contenido, no de texto.
A2: Par de documentos | B2: Pasaje compartido | C2: Que es
A3: 6601 / FAQ-ADM | B3: 1,2 EUR/MWh o 1,6 EUR/mes segun | C3: Coste de la remesa fija. Coinciden
A4: 6601 / FAQ-ADM | B4: el contacto del punto de suministro | C4: Encabezado del mismo tramite
A5: 6601 / FAQ-ADM | B5: guardar la modificacion se activa automaticamente | C5: Cierre del mismo procedimiento
A6: 6601 / FAQ-ADM | B6: modificacion de datos de contacto del | C6: Titulo de seccion identico
A7: 6601 / FAQ-ADM | B7: una cuenta existente desde el desplegable | C7: Paso identico de cuenta bancaria
A8: 6601 / FAQ-ADM | B8: 1% del coste de energia | C8: Coste remesa fija precio fijo
A9: 6601 / FAQ-CON | B9: que esperar a la renovacion o | C9: Restriccion del producto de precio fijo
A10: 6601 / FAQ-CON | B10: si el contrato esta pendiente de firma | C10: Misma casuistica de estados
A11: FAQ-ADM / FAQ-CON | B11: la cuenta bancaria de un cliente | C11: Mismo tramite
A12: FAQ-ADM / FAQ-CON | B12: la modificacion se finaliza automaticamente | C12: Mismo cierre
A13: 6292 / 6601 | B13: se generara un nuevo contrato | C13: Unica coincidencia entre tecnicas y administrativas

Sheet 03_Contradicciones
A1: Tema | B1: Riesgo | C1: Documento A | D1: Dice A | E1: Documento B | F1: Dice B | G1: Por que importa
A2: Direccion de facturacion: paso final | B2: ALTA | C2: 000006601 Sec.6.3 | D2: se pulsa "Normalizar" y despues "Guardar" | E2: FAQs MODIF ADMIN Sec.8 | F2: Pulsa "Guardar sin normalizar". Pulsa "Crear". Pulsa "Guardar" | G2: Dos pasos operativos opuestos. El agente hara uno u otro segun que documento gane el ranking
A3: Contacto del PS: telefono extranjero | B3: ALTA | C3: 000006601 Sec.5 | D3: Es obligatorio incluir un numero de telefono movil espanol valido. "Puedo introducir un telefono ingles? No" | E3: FAQs MODIF ADMIN Sec.5 | F3: No menciona ninguna restriccion de prefijo | G3: Si gana el compendio, el agente no se entera de la restriccion y la gestion fallara
A4: Monedero Solar: consecuencia de desactivar | B4: ALTA | C4: 000006601 Sec.9 | D4: "Puedo desactivar el monedero solar? Si." | E4: FAQs MODIF ADMIN Sec.11 | F4: la modificacion se finaliza automaticamente perdiendo en ese momento el importe que hubiera en el monedero solar, es decir, quedaria a 0 EUR | G4: Perdida economica para el cliente. El procedimiento oficial omite el aviso; solo lo tiene el compendio
A5: Producto de precio fijo | B5: ALTA | C5: 000006601 Sec.1 y FAQ-CON Sec.3 | D5: no se podra modificar. Sera necesario esperar a la renovacion o aplicar retencion | E5: FAQs MODIF ADMIN Sec.1 | F5: Describe como modificar el producto sin mencionar la restriccion | G5: El compendio induce a intentar una gestion imposible
A6: Tipo de firma disponible | B6: MEDIA | C6: 000006601 Sec.7 | D6: electronica presencial, electronica a distancia o en papel | E6: FAQs MODIF ADMIN Sec.9 | F6: Tipo de firma (Distancia o Presencial) | G6: Falta la opcion papel. Nuestra pregunta B10 preguntaba exactamente por esto
A7: Cuenta bancaria: cuando hace falta firma | B7: MEDIA | C7: 000006601 Sec.6.2 | D7: Si no consta firmada la cuenta en el sistema, se tendra que seleccionar "Generar documento" | E7: FAQs MODIF ADMIN Sec.7 | F7: Pulsa "Generar documento" para la firma del cliente (siempre) | G7: Condicional frente a incondicional
A8: Modificaciones simultaneas | B8: MEDIA | C8: 000006601 Intro | D8: Todas las modificaciones administrativas se pueden combinar entre ellas | E8: FAQ-CON Sec.11 | F8: Puedo hacer una modificacion en el contrato teniendo otra en curso? No, no es posible | G8: Se refieren a cosas distintas (combinar en la misma solicitud vs tener dos en curso) pero un agente que pregunte "puedo hacer dos a la vez" recibe respuestas opuestas
A9: Maximetro: terminologia de la potencia | B9: BAJA | C9: 000006292 Sec.3 | D9: la potencia debe ser la maxima del BOLETIN | E9: FAQ-CON Sec.10 y 000006590 pag.13 | F9: la maxima autorizada por el CIE | G9: Mismo concepto, dos terminos. Dificulta que el RAG los reconozca como equivalentes

Sheet 04_Recomendacion
A1: # | B1: Accion | C1: Documento | D1: Detalle
A2: 1 | B2: FUSIONAR | C2: 000006601 + FAQs MODIFICACIONES ADMINISTRATIVAS | D2: Son el mismo documento escrito dos veces: 11 de 12 temas duplicados y 6 contradicciones. Base de contenido: 000006601, que tiene las restricciones y avisos. Bloques "Ejemplo:" con lenguaje coloquial: del FAQ, que es lo que le hace ganar la recuperacion. Resolver antes las 6 contradicciones con negocio.
A3: 2 | B3: RETIRAR | C3: El que no sobreviva a la fusion | D3: Publicar el fusionado no basta: hay que despublicar el otro. Precedente: 000006590 convive con su propia version anterior bajo el mismo codigo.
A4: 3 | B4: PODAR | C4: 000006292 Modificaciones tecnicas | D4: Quitar "Datos Contrato" (el propio documento admite que es administrativa) y la mencion al Monedero Solar. Remitir al administrativo. Mismo criterio que ya se aplico al sacar los plazos de activacion de 000006590.
A5: 4 | B5: DELIMITAR | C5: 20260414 FAQs Modificaciones de contrato | D5: Su Sec.4 enumera TODAS las modificaciones, administrativas y tecnicas, lo que le hace competir con los otros tres a la vez. Dejar solo lo que es suyo: cambio de titular con modificaciones, bajas, renovacion en curso y modificacion masiva de cuenta.
A6: 5 | B6: UNIFICAR | C6: Terminologia CIE / boletin | D6: La regla de la potencia con maximetro aparece en 000006292, en FAQ-CON y en 000006590. Dejarla en un unico sitio y que los demas remitan.

Sheet 05_Estructura_FAQ
B2: La estructura FAQ, ¿sirve para todo tipo de documento?
B4: No. Sirve muy bien para una cosa concreta y falla en otras dos. LO QUE HACE BIEN: los bloques "Ejemplo:" con lenguaje coloquial del agente son lo que hace que un chunk coincida con lo que el agente escribe. Por eso el FAQs administrativo gana 14 de los primeros puestos. Ese patron deberia copiarse a TODOS los documentos. LO QUE HACE MAL: el formato pregunta-respuesta invita a contestar el caso comun y soltar las excepciones. Es medible: el FAQs administrativo omite cuatro restricciones que si estan en 000006601 (telefono espanol, producto de precio fijo, firma en papel, codigo de barras). Y un procedimiento es una secuencia con precondiciones; troceado en preguntas sueltas pierde el orden. CONCLUSION: la FAQ es un COMPLEMENTO, no un sustituto. El patron correcto es documento de procedimiento con el contenido canonico MAS un bloque de preguntas coloquiales al final. Que es casi lo que ya hace 000006601: solo le faltan mas preguntas y mas coloquiales.
A6: Tipo de documento | B6: Estructura adecuada | C6: ¿Formato FAQ? | D6: Por que
B7: Procedimiento operativo | C7: Pasos numerados + bloque FAQ al final | D7: SI, pero como complemento | E7: Los pasos necesitan orden y precondiciones. Una FAQ suelta pierde la secuencia. El bloque de preguntas coloquiales al final es lo que da recuperacion.
B8: Referencia con datos | C8: Tabla con fecha de vigencia. NO formato FAQ | D8: NO | E8: Precios, potencias normalizadas, tipos impositivos. Lo que necesitan es vigencia y estructura tabular. Es el tema n.1 de fallos y ninguna FAQ lo arregla.
B9: Concepto o definicion | C9: Definicion + No confundir con + FAQ | D9: SI | E9: Aqui la FAQ encaja bien: son preguntas independientes de verdad.
B10: Compendio multi-tramite | C10: No deberia existir | D10: NO | E10: O es un indice que remite, o son fichas. Un compendio gana la recuperacion por densidad de vocabulario y desplaza al documento especifico, aunque tenga menos detalle.
